fakedpy/__init__.py
fakedpy/generate.py
tests/__init__.py
tests/test_fakedpy.py
fakedpy-1.5.dist-info/LICENSE
fakedpy-1.5.dist-info/METADATA
fakedpy-1.5.dist-info/WHEEL
fakedpy-1.5.dist-info/top_level.txt
fakedpy-1.5.dist-info/RECORD
