Metadata-Version: 2.1
Name: fakedpy
Version: 1.5
Summary: A Python library for generating fake data with various output formats.
Home-page: UNKNOWN
Author: Arya Wiratama
Author-email: aryawiratama2401@gmail.com
License: UNKNOWN
Platform: UNKNOWN
Requires-Python: >=3.10
License-File: LICENSE
Requires-Dist: faker
Requires-Dist: openpyxl
Requires-Dist: pandas
Requires-Dist: pyarrow
